<?xml version="1.0" encoding="UTF-8" ?>
<!DOCTYPE mapper PUBLIC "-//mybatis.org//DTD Mapper 3.0//EN" "http://mybatis.org/dtd/mybatis-3-mapper.dtd" >
<mapper namespace="com.forwechat.wechatproject.dao.UserInfoDao">
    <!--auto generated Code-->
    <resultMap id="BaseResultMap" type="com.forwechat.wechatproject.pojo.UserInfo">
        <result column="id" property="id" jdbcType="BIGINT"/>
        <result column="user_name" property="userName" jdbcType="VARCHAR"/>
        <result column="name" property="name" jdbcType="VARCHAR"/>
        <result column="telephone" property="telephone" jdbcType="VARCHAR"/>
        <result column="pass_word" property="passWord" jdbcType="VARCHAR"/>
        <result column="email" property="email" jdbcType="VARCHAR"/>
        <result column="stat" property="stat" jdbcType="BIGINT"/>
        <result column="sex" property="sex" jdbcType="VARCHAR"/>
        <result column="login_ip" property="loginIp" jdbcType="VARCHAR"/>
        <result column="login_time" property="loginTime" jdbcType="TIMESTAMP"/>
        <result column="address" property="address" jdbcType="VARCHAR"/>
        <result column="identity_card" property="identityCard" jdbcType="VARCHAR"/>
        <result column="identity_card_address" property="identityCardAddress" jdbcType="VARCHAR"/>
    </resultMap>

    <!--auto generated Code-->
    <sql id="Base_Column_List">
        id,
        user_name,
        name,
        telephone,
        pass_word,
        email,
        stat,
        sex,
        login_ip,
        login_time,
        address,
        identity_card,
        identity_card_address
    </sql>

    <!--auto generated Code-->
    <insert id="insert" useGeneratedKeys="true" keyProperty="userInfo.id">
        INSERT INTO user_info (
            id,
            user_name,
            name,
            telephone,
            pass_word,
            email,
            stat,
            sex,
            login_ip,
            login_time,
            address,
            identity_card,
            identity_card_address
        ) VALUES (
            #{userInfo.id,jdbcType=BIGINT},
            #{userInfo.userName,jdbcType=VARCHAR},
            #{userInfo.name,jdbcType=VARCHAR},
            #{userInfo.telephone,jdbcType=VARCHAR},
            #{userInfo.passWord,jdbcType=VARCHAR},
            #{userInfo.email,jdbcType=VARCHAR},
            #{userInfo.stat,jdbcType=BIGINT},
            #{userInfo.sex,jdbcType=VARCHAR},
            #{userInfo.loginIp,jdbcType=VARCHAR},
            #{userInfo.loginTime,jdbcType=TIMESTAMP},
            #{userInfo.address,jdbcType=VARCHAR},
            #{userInfo.identityCard,jdbcType=VARCHAR},
            #{userInfo.identityCardAddress,jdbcType=VARCHAR}
        )
    </insert>

    <!--auto generated Code-->
    <insert id="insertSelective" useGeneratedKeys="true" keyProperty="userInfo.id">
        INSERT INTO user_info
        <trim prefix="(" suffix=")" suffixOverrides=",">
            <if test="userInfo.id!=null"> id,</if>
            <if test="userInfo.userName!=null"> user_name,</if>
            <if test="userInfo.name!=null"> name,</if>
            <if test="userInfo.telephone!=null"> telephone,</if>
            <if test="userInfo.passWord!=null"> pass_word,</if>
            <if test="userInfo.email!=null"> email,</if>
            <if test="userInfo.stat!=null"> stat,</if>
            <if test="userInfo.sex!=null"> sex,</if>
            <if test="userInfo.loginIp!=null"> login_ip,</if>
            <if test="userInfo.loginTime!=null"> login_time,</if>
            <if test="userInfo.address!=null"> address,</if>
            <if test="userInfo.identityCard!=null"> identity_card,</if>
            <if test="userInfo.identityCardAddress!=null"> identity_card_address,</if>
        </trim>
        VALUES
        <trim prefix="(" suffix=")" suffixOverrides=",">
            <if test="userInfo.id!=null">#{userInfo.id,jdbcType=BIGINT},
            </if>
            <if test="userInfo.userName!=null">#{userInfo.userName,jdbcType=VARCHAR},
            </if>
            <if test="userInfo.name!=null">#{userInfo.name,jdbcType=VARCHAR},
            </if>
            <if test="userInfo.telephone!=null">#{userInfo.telephone,jdbcType=VARCHAR},
            </if>
            <if test="userInfo.passWord!=null">#{userInfo.passWord,jdbcType=VARCHAR},
            </if>
            <if test="userInfo.email!=null">#{userInfo.email,jdbcType=VARCHAR},
            </if>
            <if test="userInfo.stat!=null">#{userInfo.stat,jdbcType=BIGINT},
            </if>
            <if test="userInfo.sex!=null">#{userInfo.sex,jdbcType=VARCHAR},
            </if>
            <if test="userInfo.loginIp!=null">#{userInfo.loginIp,jdbcType=VARCHAR},
            </if>
            <if test="userInfo.loginTime!=null">#{userInfo.loginTime,jdbcType=TIMESTAMP},
            </if>
            <if test="userInfo.address!=null">#{userInfo.address,jdbcType=VARCHAR},
            </if>
            <if test="userInfo.identityCard!=null">#{userInfo.identityCard,jdbcType=VARCHAR},
            </if>
            <if test="userInfo.identityCardAddress!=null">#{userInfo.identityCardAddress,jdbcType=VARCHAR},
            </if>
        </trim>
    </insert>

    <!--auto generated Code-->
    <insert id="insertList">
        INSERT INTO user_info (
        <include refid="Base_Column_List"/>
        )VALUES
        <foreach collection="userInfos" item="userInfo" index="index" separator=",">
            (
            #{userInfo.id,jdbcType=BIGINT},
            #{userInfo.userName,jdbcType=VARCHAR},
            #{userInfo.name,jdbcType=VARCHAR},
            #{userInfo.telephone,jdbcType=VARCHAR},
            #{userInfo.passWord,jdbcType=VARCHAR},
            #{userInfo.email,jdbcType=VARCHAR},
            #{userInfo.stat,jdbcType=BIGINT},
            #{userInfo.sex,jdbcType=VARCHAR},
            #{userInfo.loginIp,jdbcType=VARCHAR},
            #{userInfo.loginTime,jdbcType=TIMESTAMP},
            #{userInfo.address,jdbcType=VARCHAR},
            #{userInfo.identityCard,jdbcType=VARCHAR},
            #{userInfo.identityCardAddress,jdbcType=VARCHAR}
            )
        </foreach>
    </insert>

    <!--auto generated Code-->
    <update id="update">
        UPDATE user_info
        <set>
            <if test="userInfo.id != null"> id= #{userInfo.id,jdbcType=BIGINT},</if>
            <if test="userInfo.userName != null"> user_name= #{userInfo.userName,jdbcType=VARCHAR},</if>
            <if test="userInfo.name != null"> name= #{userInfo.name,jdbcType=VARCHAR},</if>
            <if test="userInfo.telephone != null"> telephone= #{userInfo.telephone,jdbcType=VARCHAR},</if>
            <if test="userInfo.passWord != null"> pass_word= #{userInfo.passWord,jdbcType=VARCHAR},</if>
            <if test="userInfo.email != null"> email= #{userInfo.email,jdbcType=VARCHAR},</if>
            <if test="userInfo.stat != null"> stat= #{userInfo.stat,jdbcType=BIGINT},</if>
            <if test="userInfo.sex != null"> sex= #{userInfo.sex,jdbcType=VARCHAR},</if>
            <if test="userInfo.loginIp != null"> login_ip= #{userInfo.loginIp,jdbcType=VARCHAR},</if>
            <if test="userInfo.loginTime != null"> login_time= #{userInfo.loginTime,jdbcType=TIMESTAMP},</if>
            <if test="userInfo.address != null"> address= #{userInfo.address,jdbcType=VARCHAR},</if>
            <if test="userInfo.identityCard != null"> identity_card= #{userInfo.identityCard,jdbcType=VARCHAR},</if>
            <if test="userInfo.identityCardAddress != null"> identity_card_address= #{userInfo.identityCardAddress,jdbcType=VARCHAR}</if>
        </set>
        WHERE id = #{userInfo.id,jdbcType=BIGINT}
    </update>

    <select id="list" resultType="com.forwechat.wechatproject.pojo.UserInfo">
        SELECT * from user_info;
    </select>
</mapper>

